hub_rest_client/__init__.py
hub_rest_client/api/__init__.py
hub_rest_client/api/default/__init__.py
hub_rest_client/api/default/delete_authmodules_authmodule_id.py
hub_rest_client/api/default/delete_authmodules_authmodule_id_autojoingroups_user_group_id.py
hub_rest_client/api/default/delete_authmodules_authmodule_id_customattributemappings_auth_module_custom_attribute_mapping_id.py
hub_rest_client/api/default/delete_authmodules_authmodule_id_groupmappings_auth_module_group_mapping_id.py
hub_rest_client/api/default/delete_certificates_certificate_id.py
hub_rest_client/api/default/delete_dashboards_dashboard_id.py
hub_rest_client/api/default/delete_dashboards_dashboard_id_permissions_dashboard_permission_id.py
hub_rest_client/api/default/delete_keystores_key_store_id.py
hub_rest_client/api/default/delete_migrations_migrations_id.py
hub_rest_client/api/default/delete_organizations_organization_id.py
hub_rest_client/api/default/delete_organizations_organization_id_groups_user_group_id.py
hub_rest_client/api/default/delete_organizations_organization_id_own_users_user_id.py
hub_rest_client/api/default/delete_organizations_organization_id_projects_project_id.py
hub_rest_client/api/default/delete_organizations_organization_id_teams_project_team_id.py
hub_rest_client/api/default/delete_organizations_organization_id_users_user_id.py
hub_rest_client/api/default/delete_permissions_permission_id.py
hub_rest_client/api/default/delete_profileattributeprototypes_profile_attribute_prototype_id.py
hub_rest_client/api/default/delete_projects_project_id.py
hub_rest_client/api/default/delete_projects_project_id_organization.py
hub_rest_client/api/default/delete_projects_project_id_resources_resource_id.py
hub_rest_client/api/default/delete_projectteams_project_team_id_groups_user_group_id.py
hub_rest_client/api/default/delete_projectteams_project_team_id_own_users_user_id.py
hub_rest_client/api/default/delete_projectteams_project_team_id_projectroles_project_role_id.py
hub_rest_client-0.1.5.dist-info/WHEEL
hub_rest_client-0.1.5.dist-info/METADATA
hub_rest_client-0.1.5.dist-info/RECORD
